BnPreprocessing/__init__.py
BnPreprocessing/bn_stopwords.txt
BnPreprocessing/example.py
BnPreprocessing/processing.py
BnPreprocessing-2.9.dist-info/LICENSE
BnPreprocessing-2.9.dist-info/METADATA
BnPreprocessing-2.9.dist-info/WHEEL
BnPreprocessing-2.9.dist-info/top_level.txt
BnPreprocessing-2.9.dist-info/RECORD
