Metadata-Version: 2.1
Name: BnPreprocessing
Version: 2.9
Summary: UNKNOWN
Home-page: https://github.com/Kowsher/Bangla-NLP/tree/master/Bangla%20Feature%20Extraction
Author: Kowsher Ahmed, Avishek Das
Author-email: ahmedshuvo969@gmail.com, avishek.das.ayan@gmail.com
License: MIT
Platform: UNKNOWN
Classifier: Programming Language :: Python :: 3
Classifier: License :: OSI Approved :: MIT License
Classifier: Operating System :: OS Independent
License-File: LICENSE
